setup.cfg
setup.py
src/pcappy/__init__.py
src/pcappy/constants.py
src/pcappy/functions.py
src/pcappy/types.py
src/pcappy.egg-info/PKG-INFO
src/pcappy.egg-info/SOURCES.txt
src/pcappy.egg-info/dependency_links.txt
src/pcappy.egg-info/not-zip-safe
src/pcappy.egg-info/top_level.txt