Metadata-Version: 1.0
Name: pcappy
Version: 0.3
Summary: Pure Python wrapper for PCAP library.
Home-page: UNKNOWN
Author: Nadeem Douba
Author-email: ndouba@gmail.com
License: GPL
Platform: UNKNOWN
